SlopeStability/__init__.py
SlopeStability/adjustment_factor.py
SlopeStability/core.py
SlopeStability/utills.py
SlopeStability/Data/B.xlsx
"SlopeStability/Data/PHI,C.xlsx"
SlopeStability/Data/PHI=0.xlsx
SlopeStability/Data/Phi_0_Increasing_shear_strength.xlsx
SlopeStability/Data/Submergence and seepage Adjustment Factor.xlsx
SlopeStability/Data/Surcharge Adjustment Factor.xlsx
SlopeStability/Data/Tension Crack Adjustment Filled with water.xlsx
SlopeStability/Data/Tension Crack Adjustment Not Filled with water.xlsx
SlopeStability-0.9.11.dist-info/METADATA
SlopeStability-0.9.11.dist-info/WHEEL
SlopeStability-0.9.11.dist-info/top_level.txt
SlopeStability-0.9.11.dist-info/RECORD
