Metadata-Version: 2.1
Name: SlopeStability
Version: 0.9.11
Summary: A package for determining factor of safety for critical slip circle using stability charts
Home-page: UNKNOWN
License: UNKNOWN
Platform: UNKNOWN
Requires-Dist: numpy
Requires-Dist: pandas
Requires-Dist: openpyxl
Requires-Dist: matplotlib
